Metadata-Version: 2.1
Name: sthg-ontology-base
Version: 0.0.26
Summary: ontology base
Home-page: https://github.com/yourusername/your_package_name
Author: DongQing
Author-email: maoyouyu@163.com
Classifier: Development Status :: 3 - Alpha
Classifier: Intended Audience :: Developers
Classifier: License :: OSI Approved :: MIT License
Classifier: Programming Language :: Python :: 3
Classifier: Programming Language :: Python :: 3.7
Classifier: Programming Language :: Python :: 3.8
Classifier: Programming Language :: Python :: 3.9
Classifier: Programming Language :: Python :: 3.10
Classifier: Programming Language :: Python :: 3.11
Classifier: Programming Language :: Python :: 3.12
Classifier: Programming Language :: Python :: 3.13
Requires-Dist: PyMySQL >=1.1.1
Requires-Dist: SQLAlchemy >=1.4.44
